setup.py
src/decipheringapi.py
src/functionapi.py
src/mqapi.py
src/otsapi.py
src/sqlapi.py
src/dkPYUtils.egg-info/PKG-INFO
src/dkPYUtils.egg-info/SOURCES.txt
src/dkPYUtils.egg-info/dependency_links.txt
src/dkPYUtils.egg-info/not-zip-safe
src/dkPYUtils.egg-info/top_level.txt